easy_db/__init__.py
easy_db/database.py
easy_db/db_types.py
easy_db/py.typed
easy_db/util.py
easy_db-0.10.2.dist-info/LICENSE.txt
easy_db-0.10.2.dist-info/METADATA
easy_db-0.10.2.dist-info/WHEEL
easy_db-0.10.2.dist-info/top_level.txt
easy_db-0.10.2.dist-info/RECORD
