Metadata-Version: 2.1
Name: easy-db
Version: 0.10.2
Summary: Easy Python database interaction
Home-page: https://github.com/zachbateman/easy_db.git
Download-URL: https://github.com/zachbateman/easy_db/archive/v_0.10.2.tar.gz
Author: Zach Bateman
License: MIT
Keywords: DATABASE,SIMPLE,EASY
Classifier: Development Status :: 4 - Beta
Classifier: License :: OSI Approved :: MIT License
Classifier: Programming Language :: Python :: 3
Classifier: Programming Language :: Python :: 3.7
Classifier: Programming Language :: Python :: 3.8
Classifier: Programming Language :: Python :: 3.9
Classifier: Programming Language :: Python :: 3.10
Classifier: Programming Language :: Python :: 3.11
Classifier: Programming Language :: Python :: 3.12
License-File: LICENSE.txt
Requires-Dist: pyodbc
Requires-Dist: tqdm
